{"schema":{"fields":[{"name":"index","type":"integer"},{"name":"danceability","type":"number"},{"name":"energy","type":"number"},{"name":"key","type":"integer"},{"name":"loudness","type":"number"},{"name":"mode","type":"integer"},{"name":"speechiness","type":"number"},{"name":"acousticness","type":"number"},{"name":"instrumentalness","type":"number"},{"name":"liveness","type":"number"},{"name":"valence","type":"number"},{"name":"tempo","type":"number"},{"name":"type","type":"string"},{"name":"id","type":"string"},{"name":"uri","type":"string"},{"name":"track_href","type":"string"},{"name":"analysis_url","type":"string"},{"name":"duration_ms","type":"integer"},{"name":"time_signature","type":"integer"},{"name":"track_name","type":"string"},{"name":"album","type":"string"},{"name":"release_date","type":"string"},{"name":"album_id","type":"string"},{"name":"artist","type":"string"}],"pandas_version":"0.20.0"},"data":[{"index":0,"danceability":0.386,"energy":0.323,"key":6,"loudness":-11.726,"mode":0,"speechiness":0.0463,"acousticness":0.874,"instrumentalness":0.00000479,"liveness":0.116,"valence":0.553,"tempo":203.638,"type":"audio_features","id":"7lXcYO7ErZqTGMrFchImcm","uri":"spotify:track:7lXcYO7ErZqTGMrFchImcm","track_href":"https:\/\/api.spotify.com\/v1\/tracks\/7lXcYO7ErZqTGMrFchImcm","analysis_url":"https:\/\/api.spotify.com\/v1\/audio-analysis\/7lXcYO7ErZqTGMrFchImcm","duration_ms":267156,"time_signature":4,"track_name":"Ez \u00fb Tu","album":"Ez \u00fb Tu","release_date":"2019-05-13","album_id":"0c9rxMdVmPzZCLpa3VvGg0","artist":"Devrim \u00c7elik"},{"index":1,"danceability":0.555,"energy":0.156,"key":10,"loudness":-14.769,"mode":1,"speechiness":0.053,"acousticness":0.956,"instrumentalness":0.0,"liveness":0.16,"valence":0.548,"tempo":108.945,"type":"audio_features","id":"1vcGlZW6U5Up8oUZk39w9X","uri":"spotify:track:1vcGlZW6U5Up8oUZk39w9X","track_href":"https:\/\/api.spotify.com\/v1\/tracks\/1vcGlZW6U5Up8oUZk39w9X","analysis_url":"https:\/\/api.spotify.com\/v1\/audio-analysis\/1vcGlZW6U5Up8oUZk39w9X","duration_ms":212026,"time_signature":4,"track_name":"Can\u00ea","album":"Ez \u00fb Tu","release_date":"2019-05-13","album_id":"0c9rxMdVmPzZCLpa3VvGg0","artist":"Devrim \u00c7elik"},{"index":2,"danceability":0.245,"energy":0.271,"key":0,"loudness":-15.107,"mode":1,"speechiness":0.0404,"acousticness":0.898,"instrumentalness":0.000175,"liveness":0.156,"valence":0.504,"tempo":197.947,"type":"audio_features","id":"6nmO2jXc30XialxINMEQIt","uri":"spotify:track:6nmO2jXc30XialxINMEQIt","track_href":"https:\/\/api.spotify.com\/v1\/tracks\/6nmO2jXc30XialxINMEQIt","analysis_url":"https:\/\/api.spotify.com\/v1\/audio-analysis\/6nmO2jXc30XialxINMEQIt","duration_ms":233777,"time_signature":4,"track_name":"B\u00eakes","album":"Ez \u00fb Tu","release_date":"2019-05-13","album_id":"0c9rxMdVmPzZCLpa3VvGg0","artist":"Devrim \u00c7elik"},{"index":3,"danceability":0.499,"energy":0.277,"key":8,"loudness":-9.832,"mode":1,"speechiness":0.0289,"acousticness":0.966,"instrumentalness":0.0000019,"liveness":0.094,"valence":0.367,"tempo":100.138,"type":"audio_features","id":"4yujkc8u6YEmOLRUOcySLm","uri":"spotify:track:4yujkc8u6YEmOLRUOcySLm","track_href":"https:\/\/api.spotify.com\/v1\/tracks\/4yujkc8u6YEmOLRUOcySLm","analysis_url":"https:\/\/api.spotify.com\/v1\/audio-analysis\/4yujkc8u6YEmOLRUOcySLm","duration_ms":234041,"time_signature":4,"track_name":"Bir\u00eendarim","album":"Ez \u00fb Tu","release_date":"2019-05-13","album_id":"0c9rxMdVmPzZCLpa3VvGg0","artist":"Devrim \u00c7elik"},{"index":4,"danceability":0.53,"energy":0.31,"key":11,"loudness":-14.086,"mode":0,"speechiness":0.0264,"acousticness":0.922,"instrumentalness":0.000101,"liveness":0.216,"valence":0.422,"tempo":99.923,"type":"audio_features","id":"4axt2IwGXDHTgMp4LcClAM","uri":"spotify:track:4axt2IwGXDHTgMp4LcClAM","track_href":"https:\/\/api.spotify.com\/v1\/tracks\/4axt2IwGXDHTgMp4LcClAM","analysis_url":"https:\/\/api.spotify.com\/v1\/audio-analysis\/4axt2IwGXDHTgMp4LcClAM","duration_ms":293052,"time_signature":4,"track_name":"Tutu\u015fur Dizelerim","album":"Ez \u00fb Tu","release_date":"2019-05-13","album_id":"0c9rxMdVmPzZCLpa3VvGg0","artist":"Devrim \u00c7elik"},{"index":5,"danceability":0.559,"energy":0.505,"key":7,"loudness":-8.345,"mode":0,"speechiness":0.0277,"acousticness":0.684,"instrumentalness":0.0000365,"liveness":0.37,"valence":0.805,"tempo":99.966,"type":"audio_features","id":"3vVuUtzeiU0T2AHQv7MKio","uri":"spotify:track:3vVuUtzeiU0T2AHQv7MKio","track_href":"https:\/\/api.spotify.com\/v1\/tracks\/3vVuUtzeiU0T2AHQv7MKio","analysis_url":"https:\/\/api.spotify.com\/v1\/audio-analysis\/3vVuUtzeiU0T2AHQv7MKio","duration_ms":160483,"time_signature":4,"track_name":"Ay Lo Dilo","album":"Ez \u00fb Tu","release_date":"2019-05-13","album_id":"0c9rxMdVmPzZCLpa3VvGg0","artist":"Devrim \u00c7elik"},{"index":6,"danceability":0.576,"energy":0.121,"key":4,"loudness":-11.254,"mode":0,"speechiness":0.142,"acousticness":0.964,"instrumentalness":0.00000181,"liveness":0.0968,"valence":0.598,"tempo":92.928,"type":"audio_features","id":"43vdS06GbSU9qBdBoL0dx1","uri":"spotify:track:43vdS06GbSU9qBdBoL0dx1","track_href":"https:\/\/api.spotify.com\/v1\/tracks\/43vdS06GbSU9qBdBoL0dx1","analysis_url":"https:\/\/api.spotify.com\/v1\/audio-analysis\/43vdS06GbSU9qBdBoL0dx1","duration_ms":135023,"time_signature":4,"track_name":"P\u00ea\u015fiya Mal\u00ea","album":"Ez \u00fb Tu","release_date":"2019-05-13","album_id":"0c9rxMdVmPzZCLpa3VvGg0","artist":"Devrim \u00c7elik"},{"index":7,"danceability":0.704,"energy":0.482,"key":7,"loudness":-13.185,"mode":0,"speechiness":0.0321,"acousticness":0.865,"instrumentalness":0.0000316,"liveness":0.105,"valence":0.792,"tempo":150.02,"type":"audio_features","id":"65hMLhKRGCArbUJ8Tbn03y","uri":"spotify:track:65hMLhKRGCArbUJ8Tbn03y","track_href":"https:\/\/api.spotify.com\/v1\/tracks\/65hMLhKRGCArbUJ8Tbn03y","analysis_url":"https:\/\/api.spotify.com\/v1\/audio-analysis\/65hMLhKRGCArbUJ8Tbn03y","duration_ms":183033,"time_signature":3,"track_name":"Wer Nine","album":"Ez \u00fb Tu","release_date":"2019-05-13","album_id":"0c9rxMdVmPzZCLpa3VvGg0","artist":"Devrim \u00c7elik"},{"index":8,"danceability":0.554,"energy":0.474,"key":10,"loudness":-8.425,"mode":0,"speechiness":0.031,"acousticness":0.91,"instrumentalness":0.000395,"liveness":0.121,"valence":0.657,"tempo":99.832,"type":"audio_features","id":"4RuwRT8zoZbYxJ5mjnMQSW","uri":"spotify:track:4RuwRT8zoZbYxJ5mjnMQSW","track_href":"https:\/\/api.spotify.com\/v1\/tracks\/4RuwRT8zoZbYxJ5mjnMQSW","analysis_url":"https:\/\/api.spotify.com\/v1\/audio-analysis\/4RuwRT8zoZbYxJ5mjnMQSW","duration_ms":248197,"time_signature":4,"track_name":"Deveyi D\u00fczde G\u00f6rd\u00fcm","album":"Ez \u00fb Tu","release_date":"2019-05-13","album_id":"0c9rxMdVmPzZCLpa3VvGg0","artist":"Devrim \u00c7elik"},{"index":9,"danceability":0.625,"energy":0.338,"key":11,"loudness":-16.611,"mode":0,"speechiness":0.0434,"acousticness":0.83,"instrumentalness":0.0000374,"liveness":0.211,"valence":0.424,"tempo":111.962,"type":"audio_features","id":"1WEdgQhj9HkMYXXCv6QR1C","uri":"spotify:track:1WEdgQhj9HkMYXXCv6QR1C","track_href":"https:\/\/api.spotify.com\/v1\/tracks\/1WEdgQhj9HkMYXXCv6QR1C","analysis_url":"https:\/\/api.spotify.com\/v1\/audio-analysis\/1WEdgQhj9HkMYXXCv6QR1C","duration_ms":312107,"time_signature":4,"track_name":"Delal\u00ea","album":"Ez \u00fb Tu","release_date":"2019-05-13","album_id":"0c9rxMdVmPzZCLpa3VvGg0","artist":"Devrim \u00c7elik"},{"index":0,"danceability":0.599,"energy":0.486,"key":7,"loudness":-11.353,"mode":0,"speechiness":0.0349,"acousticness":0.797,"instrumentalness":0.00000454,"liveness":0.543,"valence":0.464,"tempo":108.024,"type":"audio_features","id":"1Knh8CesKjPAeynlWE9owO","uri":"spotify:track:1Knh8CesKjPAeynlWE9owO","track_href":"https:\/\/api.spotify.com\/v1\/tracks\/1Knh8CesKjPAeynlWE9owO","analysis_url":"https:\/\/api.spotify.com\/v1\/audio-analysis\/1Knh8CesKjPAeynlWE9owO","duration_ms":278361,"time_signature":4,"track_name":"E\u015f\u00eereta Kony\u00ea","album":"E\u015f\u00eereta Kony\u00ea","release_date":"2020-06-25","album_id":"0ANRO9dlmAROlFDWrMmCUM","artist":"Devrim \u00c7elik"},{"index":0,"danceability":0.424,"energy":0.37,"key":11,"loudness":-13.972,"mode":0,"speechiness":0.0337,"acousticness":0.717,"instrumentalness":0.00000483,"liveness":0.219,"valence":0.66,"tempo":169.685,"type":"audio_features","id":"13bLhAHzGIGcThx8Cntdnp","uri":"spotify:track:13bLhAHzGIGcThx8Cntdnp","track_href":"https:\/\/api.spotify.com\/v1\/tracks\/13bLhAHzGIGcThx8Cntdnp","analysis_url":"https:\/\/api.spotify.com\/v1\/audio-analysis\/13bLhAHzGIGcThx8Cntdnp","duration_ms":264522,"time_signature":4,"track_name":"Pay\u00eeza Min","album":"Pay\u00eeza Min","release_date":"2019-12-12","album_id":"1FpO4LMzhc5K48PNueYNT8","artist":"Devrim \u00c7elik"},{"index":0,"danceability":0.391,"energy":0.279,"key":0,"loudness":-14.265,"mode":1,"speechiness":0.033,"acousticness":0.884,"instrumentalness":0.0000507,"liveness":0.111,"valence":0.686,"tempo":104.992,"type":"audio_features","id":"5KYV4hiziEsyEWVKaaAOQ2","uri":"spotify:track:5KYV4hiziEsyEWVKaaAOQ2","track_href":"https:\/\/api.spotify.com\/v1\/tracks\/5KYV4hiziEsyEWVKaaAOQ2","analysis_url":"https:\/\/api.spotify.com\/v1\/audio-analysis\/5KYV4hiziEsyEWVKaaAOQ2","duration_ms":258882,"time_signature":3,"track_name":"Min Ne Got","album":"Min Ne Got","release_date":"2019-10-17","album_id":"4VV3v1xdWvKWQZKnWbHUSV","artist":"Devrim \u00c7elik"},{"index":0,"danceability":0.562,"energy":0.355,"key":1,"loudness":-13.914,"mode":1,"speechiness":0.0333,"acousticness":0.739,"instrumentalness":0.0000932,"liveness":0.278,"valence":0.461,"tempo":115.096,"type":"audio_features","id":"7eGZxjWQ0afsxpefiYRvR6","uri":"spotify:track:7eGZxjWQ0afsxpefiYRvR6","track_href":"https:\/\/api.spotify.com\/v1\/tracks\/7eGZxjWQ0afsxpefiYRvR6","analysis_url":"https:\/\/api.spotify.com\/v1\/audio-analysis\/7eGZxjWQ0afsxpefiYRvR6","duration_ms":223304,"time_signature":4,"track_name":"\u00c7avre\u015f\u00ea","album":"\u00c7avre\u015f\u00ea","release_date":"2019-10-03","album_id":"7esOiBfAUKzzfH7rx9DAc8","artist":"Devrim \u00c7elik"},{"index":0,"danceability":0.554,"energy":0.37,"key":6,"loudness":-10.344,"mode":0,"speechiness":0.0282,"acousticness":0.862,"instrumentalness":0.0000202,"liveness":0.128,"valence":0.43,"tempo":96.095,"type":"audio_features","id":"04A5egVUR6wPISwM8EOnOJ","uri":"spotify:track:04A5egVUR6wPISwM8EOnOJ","track_href":"https:\/\/api.spotify.com\/v1\/tracks\/04A5egVUR6wPISwM8EOnOJ","analysis_url":"https:\/\/api.spotify.com\/v1\/audio-analysis\/04A5egVUR6wPISwM8EOnOJ","duration_ms":264243,"time_signature":3,"track_name":"\u015eu Tepe Pullu Tepe","album":"\u015eu Tepe Pullu Tepe","release_date":"2019-07-31","album_id":"5xDo66AWR17p5rvnq3cleE","artist":"Devrim \u00c7elik"},{"index":0,"danceability":0.657,"energy":0.823,"key":9,"loudness":-3.887,"mode":0,"speechiness":0.0299,"acousticness":0.0653,"instrumentalness":0.0000487,"liveness":0.206,"valence":0.651,"tempo":115.082,"type":"audio_features","id":"6hWKVNNXDu3FOkFEtThcpE","uri":"spotify:track:6hWKVNNXDu3FOkFEtThcpE","track_href":"https:\/\/api.spotify.com\/v1\/tracks\/6hWKVNNXDu3FOkFEtThcpE","analysis_url":"https:\/\/api.spotify.com\/v1\/audio-analysis\/6hWKVNNXDu3FOkFEtThcpE","duration_ms":263998,"time_signature":4,"track_name":"Zul\u00fcm Kokar","album":"Zul\u00fcm Kokar","release_date":"2019-04-11","album_id":"3oNhgumbQ1bkm4N5Xic51f","artist":"Devrim \u00c7elik"}]}