{"schema":{"fields":[{"name":"index","type":"integer"},{"name":"danceability","type":"number"},{"name":"energy","type":"number"},{"name":"key","type":"integer"},{"name":"loudness","type":"number"},{"name":"mode","type":"integer"},{"name":"speechiness","type":"number"},{"name":"acousticness","type":"number"},{"name":"instrumentalness","type":"number"},{"name":"liveness","type":"number"},{"name":"valence","type":"number"},{"name":"tempo","type":"number"},{"name":"type","type":"string"},{"name":"id","type":"string"},{"name":"uri","type":"string"},{"name":"track_href","type":"string"},{"name":"analysis_url","type":"string"},{"name":"duration_ms","type":"integer"},{"name":"time_signature","type":"integer"},{"name":"track_name","type":"string"},{"name":"album","type":"string"},{"name":"release_date","type":"string"},{"name":"album_id","type":"string"},{"name":"artist","type":"string"}],"pandas_version":"0.20.0"},"data":[{"index":0,"danceability":0.273,"energy":0.82,"key":11,"loudness":-6.65,"mode":0,"speechiness":0.0506,"acousticness":0.0483,"instrumentalness":0.00000568,"liveness":0.112,"valence":0.602,"tempo":70.563,"type":"audio_features","id":"5WpaeKlvrFgYLxmIurENTC","uri":"spotify:track:5WpaeKlvrFgYLxmIurENTC","track_href":"https:\/\/api.spotify.com\/v1\/tracks\/5WpaeKlvrFgYLxmIurENTC","analysis_url":"https:\/\/api.spotify.com\/v1\/audio-analysis\/5WpaeKlvrFgYLxmIurENTC","duration_ms":273611,"time_signature":4,"track_name":"Intro","album":"Xperimental","release_date":"2016-09-19","album_id":"3bIruYdko3AXbV4WvtXzjY","artist":"Flaka Krelani"},{"index":1,"danceability":0.481,"energy":0.771,"key":2,"loudness":-3.199,"mode":1,"speechiness":0.0475,"acousticness":0.272,"instrumentalness":0.0,"liveness":0.133,"valence":0.381,"tempo":79.074,"type":"audio_features","id":"2tqqvxa57oE7VkAc1YxxVi","uri":"spotify:track:2tqqvxa57oE7VkAc1YxxVi","track_href":"https:\/\/api.spotify.com\/v1\/tracks\/2tqqvxa57oE7VkAc1YxxVi","analysis_url":"https:\/\/api.spotify.com\/v1\/audio-analysis\/2tqqvxa57oE7VkAc1YxxVi","duration_ms":211000,"time_signature":4,"track_name":"Zjam","album":"Xperimental","release_date":"2016-09-19","album_id":"3bIruYdko3AXbV4WvtXzjY","artist":"Flaka Krelani"},{"index":2,"danceability":0.573,"energy":0.82,"key":6,"loudness":-6.173,"mode":0,"speechiness":0.113,"acousticness":0.341,"instrumentalness":0.0,"liveness":0.172,"valence":0.61,"tempo":103.622,"type":"audio_features","id":"5kaJMIahINia6M4sn42jmr","uri":"spotify:track:5kaJMIahINia6M4sn42jmr","track_href":"https:\/\/api.spotify.com\/v1\/tracks\/5kaJMIahINia6M4sn42jmr","analysis_url":"https:\/\/api.spotify.com\/v1\/audio-analysis\/5kaJMIahINia6M4sn42jmr","duration_ms":198000,"time_signature":4,"track_name":"E Di","album":"Xperimental","release_date":"2016-09-19","album_id":"3bIruYdko3AXbV4WvtXzjY","artist":"Flaka Krelani"},{"index":3,"danceability":0.673,"energy":0.455,"key":1,"loudness":-8.632,"mode":1,"speechiness":0.0292,"acousticness":0.0633,"instrumentalness":0.00000146,"liveness":0.119,"valence":0.177,"tempo":111.01,"type":"audio_features","id":"5FsG2PeHHYYeVGGMIVF6NF","uri":"spotify:track:5FsG2PeHHYYeVGGMIVF6NF","track_href":"https:\/\/api.spotify.com\/v1\/tracks\/5FsG2PeHHYYeVGGMIVF6NF","analysis_url":"https:\/\/api.spotify.com\/v1\/audio-analysis\/5FsG2PeHHYYeVGGMIVF6NF","duration_ms":220504,"time_signature":4,"track_name":"Hit Me","album":"Xperimental","release_date":"2016-09-19","album_id":"3bIruYdko3AXbV4WvtXzjY","artist":"Flaka Krelani"},{"index":4,"danceability":0.518,"energy":0.691,"key":0,"loudness":-7.453,"mode":1,"speechiness":0.0372,"acousticness":0.211,"instrumentalness":0.138,"liveness":0.122,"valence":0.0724,"tempo":115.051,"type":"audio_features","id":"302jRR5SjsApjSO7TcYdSO","uri":"spotify:track:302jRR5SjsApjSO7TcYdSO","track_href":"https:\/\/api.spotify.com\/v1\/tracks\/302jRR5SjsApjSO7TcYdSO","analysis_url":"https:\/\/api.spotify.com\/v1\/audio-analysis\/302jRR5SjsApjSO7TcYdSO","duration_ms":348001,"time_signature":4,"track_name":"Edhe Sa","album":"Xperimental","release_date":"2016-09-19","album_id":"3bIruYdko3AXbV4WvtXzjY","artist":"Flaka Krelani"},{"index":5,"danceability":0.533,"energy":0.931,"key":1,"loudness":-3.67,"mode":0,"speechiness":0.102,"acousticness":0.0027,"instrumentalness":0.0,"liveness":0.216,"valence":0.711,"tempo":142.868,"type":"audio_features","id":"3iXZYxJOZk1VG3alI6kXGY","uri":"spotify:track:3iXZYxJOZk1VG3alI6kXGY","track_href":"https:\/\/api.spotify.com\/v1\/tracks\/3iXZYxJOZk1VG3alI6kXGY","analysis_url":"https:\/\/api.spotify.com\/v1\/audio-analysis\/3iXZYxJOZk1VG3alI6kXGY","duration_ms":211622,"time_signature":4,"track_name":"Am I Good Man","album":"Xperimental","release_date":"2016-09-19","album_id":"3bIruYdko3AXbV4WvtXzjY","artist":"Flaka Krelani"},{"index":6,"danceability":0.541,"energy":0.7,"key":6,"loudness":-5.62,"mode":0,"speechiness":0.0819,"acousticness":0.0602,"instrumentalness":0.0,"liveness":0.247,"valence":0.519,"tempo":100.156,"type":"audio_features","id":"0TeZwYeFrPQhkMzc4IGB6y","uri":"spotify:track:0TeZwYeFrPQhkMzc4IGB6y","track_href":"https:\/\/api.spotify.com\/v1\/tracks\/0TeZwYeFrPQhkMzc4IGB6y","analysis_url":"https:\/\/api.spotify.com\/v1\/audio-analysis\/0TeZwYeFrPQhkMzc4IGB6y","duration_ms":237462,"time_signature":4,"track_name":"Ti (feat. J.Pak)","album":"Xperimental","release_date":"2016-09-19","album_id":"3bIruYdko3AXbV4WvtXzjY","artist":"Flaka Krelani"},{"index":7,"danceability":0.86,"energy":0.532,"key":10,"loudness":-9.245,"mode":0,"speechiness":0.176,"acousticness":0.207,"instrumentalness":0.0000177,"liveness":0.156,"valence":0.792,"tempo":123.961,"type":"audio_features","id":"74KOb6qMxW1kqX5ETdjGw2","uri":"spotify:track:74KOb6qMxW1kqX5ETdjGw2","track_href":"https:\/\/api.spotify.com\/v1\/tracks\/74KOb6qMxW1kqX5ETdjGw2","analysis_url":"https:\/\/api.spotify.com\/v1\/audio-analysis\/74KOb6qMxW1kqX5ETdjGw2","duration_ms":247616,"time_signature":4,"track_name":"Funky Funk","album":"Xperimental","release_date":"2016-09-19","album_id":"3bIruYdko3AXbV4WvtXzjY","artist":"Flaka Krelani"},{"index":8,"danceability":0.564,"energy":0.639,"key":9,"loudness":-10.123,"mode":1,"speechiness":0.0553,"acousticness":0.0498,"instrumentalness":0.013,"liveness":0.111,"valence":0.0391,"tempo":139.533,"type":"audio_features","id":"2K1AMmu6ALhJRB4iU9q4KM","uri":"spotify:track:2K1AMmu6ALhJRB4iU9q4KM","track_href":"https:\/\/api.spotify.com\/v1\/tracks\/2K1AMmu6ALhJRB4iU9q4KM","analysis_url":"https:\/\/api.spotify.com\/v1\/audio-analysis\/2K1AMmu6ALhJRB4iU9q4KM","duration_ms":272019,"time_signature":4,"track_name":"Ngrihu Tash","album":"Xperimental","release_date":"2016-09-19","album_id":"3bIruYdko3AXbV4WvtXzjY","artist":"Flaka Krelani"},{"index":9,"danceability":0.798,"energy":0.612,"key":2,"loudness":-6.564,"mode":1,"speechiness":0.04,"acousticness":0.004,"instrumentalness":0.00000774,"liveness":0.0796,"valence":0.363,"tempo":114.976,"type":"audio_features","id":"0ACZ0sdel9MD5haf1dkI6K","uri":"spotify:track:0ACZ0sdel9MD5haf1dkI6K","track_href":"https:\/\/api.spotify.com\/v1\/tracks\/0ACZ0sdel9MD5haf1dkI6K","analysis_url":"https:\/\/api.spotify.com\/v1\/audio-analysis\/0ACZ0sdel9MD5haf1dkI6K","duration_ms":232000,"time_signature":4,"track_name":"Relax","album":"Xperimental","release_date":"2016-09-19","album_id":"3bIruYdko3AXbV4WvtXzjY","artist":"Flaka Krelani"},{"index":10,"danceability":0.392,"energy":0.952,"key":1,"loudness":-4.619,"mode":1,"speechiness":0.368,"acousticness":0.0398,"instrumentalness":0.0,"liveness":0.127,"valence":0.26,"tempo":129.168,"type":"audio_features","id":"4tsfwmaYUK9xgpw1lXeVo3","uri":"spotify:track:4tsfwmaYUK9xgpw1lXeVo3","track_href":"https:\/\/api.spotify.com\/v1\/tracks\/4tsfwmaYUK9xgpw1lXeVo3","analysis_url":"https:\/\/api.spotify.com\/v1\/audio-analysis\/4tsfwmaYUK9xgpw1lXeVo3","duration_ms":283975,"time_signature":3,"track_name":"Jan Qu Fjalt E Urta Pesh","album":"Xperimental","release_date":"2016-09-19","album_id":"3bIruYdko3AXbV4WvtXzjY","artist":"Flaka Krelani"},{"index":11,"danceability":0.551,"energy":0.626,"key":4,"loudness":-8.069,"mode":0,"speechiness":0.32,"acousticness":0.21,"instrumentalness":0.0,"liveness":0.13,"valence":0.212,"tempo":138.932,"type":"audio_features","id":"7wOL70s8m4PT40GIkCzozG","uri":"spotify:track:7wOL70s8m4PT40GIkCzozG","track_href":"https:\/\/api.spotify.com\/v1\/tracks\/7wOL70s8m4PT40GIkCzozG","analysis_url":"https:\/\/api.spotify.com\/v1\/audio-analysis\/7wOL70s8m4PT40GIkCzozG","duration_ms":258000,"time_signature":4,"track_name":"A Ka Kuptim","album":"Xperimental","release_date":"2016-09-19","album_id":"3bIruYdko3AXbV4WvtXzjY","artist":"Flaka Krelani"},{"index":12,"danceability":0.517,"energy":0.607,"key":2,"loudness":-8.381,"mode":1,"speechiness":0.0735,"acousticness":0.0075,"instrumentalness":0.0000967,"liveness":0.155,"valence":0.191,"tempo":164.963,"type":"audio_features","id":"0C8EHArtiO03h5siWCBgWD","uri":"spotify:track:0C8EHArtiO03h5siWCBgWD","track_href":"https:\/\/api.spotify.com\/v1\/tracks\/0C8EHArtiO03h5siWCBgWD","analysis_url":"https:\/\/api.spotify.com\/v1\/audio-analysis\/0C8EHArtiO03h5siWCBgWD","duration_ms":250069,"time_signature":4,"track_name":"Un","album":"Xperimental","release_date":"2016-09-19","album_id":"3bIruYdko3AXbV4WvtXzjY","artist":"Flaka Krelani"},{"index":13,"danceability":0.403,"energy":0.724,"key":11,"loudness":-7.082,"mode":0,"speechiness":0.242,"acousticness":0.00355,"instrumentalness":0.0,"liveness":0.0507,"valence":0.562,"tempo":78.172,"type":"audio_features","id":"0dF904mn22j2k1tfO8NxsL","uri":"spotify:track:0dF904mn22j2k1tfO8NxsL","track_href":"https:\/\/api.spotify.com\/v1\/tracks\/0dF904mn22j2k1tfO8NxsL","analysis_url":"https:\/\/api.spotify.com\/v1\/audio-analysis\/0dF904mn22j2k1tfO8NxsL","duration_ms":244584,"time_signature":1,"track_name":"Fire","album":"Xperimental","release_date":"2016-09-19","album_id":"3bIruYdko3AXbV4WvtXzjY","artist":"Flaka Krelani"},{"index":14,"danceability":0.413,"energy":0.594,"key":2,"loudness":-10.821,"mode":1,"speechiness":0.0492,"acousticness":0.0021,"instrumentalness":0.0179,"liveness":0.076,"valence":0.344,"tempo":114.968,"type":"audio_features","id":"61kPtGzYIjyh4DjKGIlYE2","uri":"spotify:track:61kPtGzYIjyh4DjKGIlYE2","track_href":"https:\/\/api.spotify.com\/v1\/tracks\/61kPtGzYIjyh4DjKGIlYE2","analysis_url":"https:\/\/api.spotify.com\/v1\/audio-analysis\/61kPtGzYIjyh4DjKGIlYE2","duration_ms":288000,"time_signature":4,"track_name":"Relax (Deep House Remix)","album":"Xperimental","release_date":"2016-09-19","album_id":"3bIruYdko3AXbV4WvtXzjY","artist":"Flaka Krelani"},{"index":15,"danceability":0.673,"energy":0.614,"key":2,"loudness":-8.423,"mode":1,"speechiness":0.0614,"acousticness":0.0139,"instrumentalness":0.000332,"liveness":0.0809,"valence":0.351,"tempo":157.948,"type":"audio_features","id":"4M1OsMjMhExsDnrxkqk9te","uri":"spotify:track:4M1OsMjMhExsDnrxkqk9te","track_href":"https:\/\/api.spotify.com\/v1\/tracks\/4M1OsMjMhExsDnrxkqk9te","analysis_url":"https:\/\/api.spotify.com\/v1\/audio-analysis\/4M1OsMjMhExsDnrxkqk9te","duration_ms":238524,"time_signature":4,"track_name":"Zjam (Trap\/Club Remix)","album":"Xperimental","release_date":"2016-09-19","album_id":"3bIruYdko3AXbV4WvtXzjY","artist":"Flaka Krelani"},{"index":0,"danceability":0.757,"energy":0.761,"key":10,"loudness":-3.095,"mode":0,"speechiness":0.0784,"acousticness":0.382,"instrumentalness":0.00000151,"liveness":0.133,"valence":0.543,"tempo":120.011,"type":"audio_features","id":"2ookP64dKe7byd4JgKm2Kb","uri":"spotify:track:2ookP64dKe7byd4JgKm2Kb","track_href":"https:\/\/api.spotify.com\/v1\/tracks\/2ookP64dKe7byd4JgKm2Kb","analysis_url":"https:\/\/api.spotify.com\/v1\/audio-analysis\/2ookP64dKe7byd4JgKm2Kb","duration_ms":215956,"time_signature":4,"track_name":"Travesuras","album":"Travesuras","release_date":"2020-07-03","album_id":"4eus2l0OjyaRbYdbKYGTuB","artist":"Flaka Krelani"},{"index":0,"danceability":0.661,"energy":0.614,"key":1,"loudness":-8.527,"mode":1,"speechiness":0.128,"acousticness":0.0598,"instrumentalness":0.0,"liveness":0.213,"valence":0.544,"tempo":151.943,"type":"audio_features","id":"4lke4PP4eIL1qbkPu4eAVD","uri":"spotify:track:4lke4PP4eIL1qbkPu4eAVD","track_href":"https:\/\/api.spotify.com\/v1\/tracks\/4lke4PP4eIL1qbkPu4eAVD","analysis_url":"https:\/\/api.spotify.com\/v1\/audio-analysis\/4lke4PP4eIL1qbkPu4eAVD","duration_ms":190356,"time_signature":4,"track_name":"Gun Shot","album":"Gun Shot","release_date":"2020-05-11","album_id":"5UPsrQ4UXArdzG0IVTiqzZ","artist":"Flaka Krelani"},{"index":0,"danceability":0.606,"energy":0.537,"key":0,"loudness":-10.977,"mode":1,"speechiness":0.0622,"acousticness":0.0789,"instrumentalness":0.00000134,"liveness":0.0958,"valence":0.37,"tempo":95.077,"type":"audio_features","id":"188Oo7ZIxfbIfUHiObd2sF","uri":"spotify:track:188Oo7ZIxfbIfUHiObd2sF","track_href":"https:\/\/api.spotify.com\/v1\/tracks\/188Oo7ZIxfbIfUHiObd2sF","analysis_url":"https:\/\/api.spotify.com\/v1\/audio-analysis\/188Oo7ZIxfbIfUHiObd2sF","duration_ms":182139,"time_signature":4,"track_name":"KTMD","album":"KTMD","release_date":"2020-04-27","album_id":"3f70EY7R5x8HpWYwdV7r33","artist":"Flaka Krelani"},{"index":0,"danceability":0.76,"energy":0.458,"key":5,"loudness":-8.869,"mode":0,"speechiness":0.0543,"acousticness":0.384,"instrumentalness":0.000141,"liveness":0.112,"valence":0.515,"tempo":129.926,"type":"audio_features","id":"7ELHalbo0gcAl6gXzVYoDn","uri":"spotify:track:7ELHalbo0gcAl6gXzVYoDn","track_href":"https:\/\/api.spotify.com\/v1\/tracks\/7ELHalbo0gcAl6gXzVYoDn","analysis_url":"https:\/\/api.spotify.com\/v1\/audio-analysis\/7ELHalbo0gcAl6gXzVYoDn","duration_ms":182793,"time_signature":4,"track_name":"Dit e Nat","album":"Dit e Nat","release_date":"2020-04-20","album_id":"54fuYk5RG3ojCBlZjt133L","artist":"Flaka Krelani"},{"index":0,"danceability":0.406,"energy":0.827,"key":8,"loudness":-6.326,"mode":0,"speechiness":0.256,"acousticness":0.0359,"instrumentalness":0.00000658,"liveness":0.0862,"valence":0.715,"tempo":163.92,"type":"audio_features","id":"4BLWqoZTVevWVhdrrKLSFq","uri":"spotify:track:4BLWqoZTVevWVhdrrKLSFq","track_href":"https:\/\/api.spotify.com\/v1\/tracks\/4BLWqoZTVevWVhdrrKLSFq","analysis_url":"https:\/\/api.spotify.com\/v1\/audio-analysis\/4BLWqoZTVevWVhdrrKLSFq","duration_ms":190259,"time_signature":4,"track_name":"Playa","album":"Playa","release_date":"2020-01-12","album_id":"6MJdhjxgP1Po0diSDqvcHX","artist":"Flaka Krelani"},{"index":0,"danceability":0.677,"energy":0.453,"key":2,"loudness":-12.387,"mode":1,"speechiness":0.0948,"acousticness":0.000363,"instrumentalness":0.105,"liveness":0.382,"valence":0.359,"tempo":196.002,"type":"audio_features","id":"5f1DprkiilnWoi8bpEVF4q","uri":"spotify:track:5f1DprkiilnWoi8bpEVF4q","track_href":"https:\/\/api.spotify.com\/v1\/tracks\/5f1DprkiilnWoi8bpEVF4q","analysis_url":"https:\/\/api.spotify.com\/v1\/audio-analysis\/5f1DprkiilnWoi8bpEVF4q","duration_ms":205737,"time_signature":4,"track_name":"Slay","album":"Slay","release_date":"2019-06-14","album_id":"3PVDQizBwfdNowYPpmrE5R","artist":"Flaka Krelani"},{"index":0,"danceability":0.79,"energy":0.562,"key":1,"loudness":-10.795,"mode":0,"speechiness":0.0357,"acousticness":0.138,"instrumentalness":0.016,"liveness":0.168,"valence":0.605,"tempo":133.99,"type":"audio_features","id":"1StTcHQMreR5elIAOLwn9b","uri":"spotify:track:1StTcHQMreR5elIAOLwn9b","track_href":"https:\/\/api.spotify.com\/v1\/tracks\/1StTcHQMreR5elIAOLwn9b","analysis_url":"https:\/\/api.spotify.com\/v1\/audio-analysis\/1StTcHQMreR5elIAOLwn9b","duration_ms":234812,"time_signature":4,"track_name":"Thell","album":"Thell","release_date":"2019-03-05","album_id":"2wgwd05Kafk27CXpPvmsSE","artist":"Flaka Krelani"},{"index":0,"danceability":0.5,"energy":0.901,"key":8,"loudness":-6.649,"mode":1,"speechiness":0.341,"acousticness":0.283,"instrumentalness":0.0,"liveness":0.604,"valence":0.123,"tempo":170.952,"type":"audio_features","id":"4BhuGoqrUpwiZuUjKhJKdE","uri":"spotify:track:4BhuGoqrUpwiZuUjKhJKdE","track_href":"https:\/\/api.spotify.com\/v1\/tracks\/4BhuGoqrUpwiZuUjKhJKdE","analysis_url":"https:\/\/api.spotify.com\/v1\/audio-analysis\/4BhuGoqrUpwiZuUjKhJKdE","duration_ms":213951,"time_signature":4,"track_name":"Garden","album":"Garden","release_date":"2018-12-07","album_id":"1ObDEnowVXBp5ssRyfY3i3","artist":"Flaka Krelani"},{"index":0,"danceability":0.65,"energy":0.787,"key":8,"loudness":-6.506,"mode":1,"speechiness":0.168,"acousticness":0.355,"instrumentalness":0.0,"liveness":0.0859,"valence":0.55,"tempo":169.938,"type":"audio_features","id":"0K2JWcybpE7HBLBihnulQd","uri":"spotify:track:0K2JWcybpE7HBLBihnulQd","track_href":"https:\/\/api.spotify.com\/v1\/tracks\/0K2JWcybpE7HBLBihnulQd","analysis_url":"https:\/\/api.spotify.com\/v1\/audio-analysis\/0K2JWcybpE7HBLBihnulQd","duration_ms":172250,"time_signature":4,"track_name":"Vet'ME","album":"Vet'ME","release_date":"2018-10-08","album_id":"2uS0mpchVffTD4EBMxpRgg","artist":"Flaka Krelani"},{"index":0,"danceability":0.416,"energy":0.764,"key":11,"loudness":-6.405,"mode":0,"speechiness":0.0964,"acousticness":0.367,"instrumentalness":0.0,"liveness":0.482,"valence":0.388,"tempo":134.007,"type":"audio_features","id":"0LlapicQt7f49ppzj0RKiH","uri":"spotify:track:0LlapicQt7f49ppzj0RKiH","track_href":"https:\/\/api.spotify.com\/v1\/tracks\/0LlapicQt7f49ppzj0RKiH","analysis_url":"https:\/\/api.spotify.com\/v1\/audio-analysis\/0LlapicQt7f49ppzj0RKiH","duration_ms":236082,"time_signature":4,"track_name":"Ndrysho","album":"Ndrysho","release_date":"2018-10-04","album_id":"00eKL6otw3SA6l4VKzPBss","artist":"Flaka Krelani"},{"index":0,"danceability":0.633,"energy":0.839,"key":5,"loudness":-5.32,"mode":0,"speechiness":0.0618,"acousticness":0.0137,"instrumentalness":0.0,"liveness":0.0393,"valence":0.801,"tempo":140.085,"type":"audio_features","id":"0O8I0NM1T4ick7kN6zcRqz","uri":"spotify:track:0O8I0NM1T4ick7kN6zcRqz","track_href":"https:\/\/api.spotify.com\/v1\/tracks\/0O8I0NM1T4ick7kN6zcRqz","analysis_url":"https:\/\/api.spotify.com\/v1\/audio-analysis\/0O8I0NM1T4ick7kN6zcRqz","duration_ms":196888,"time_signature":4,"track_name":"Def Star (feat. Pancho City)","album":"Def Star","release_date":"2017-11-17","album_id":"3Ahvc2CSO6l7Zd2wOjE0Qv","artist":"Flaka Krelani"},{"index":0,"danceability":0.796,"energy":0.598,"key":2,"loudness":-7.083,"mode":1,"speechiness":0.0337,"acousticness":0.0033,"instrumentalness":0.0000229,"liveness":0.0859,"valence":0.37,"tempo":115.001,"type":"audio_features","id":"0vqg5OXg2t7qgQ5fBj1hOc","uri":"spotify:track:0vqg5OXg2t7qgQ5fBj1hOc","track_href":"https:\/\/api.spotify.com\/v1\/tracks\/0vqg5OXg2t7qgQ5fBj1hOc","analysis_url":"https:\/\/api.spotify.com\/v1\/audio-analysis\/0vqg5OXg2t7qgQ5fBj1hOc","duration_ms":232000,"time_signature":4,"track_name":"Relax","album":"Relax","release_date":"2016-03-04","album_id":"3Um9S9rn6A5AimQEXzBNij","artist":"Flaka Krelani"}]}